logs/__init__.py
logs/configure.py
harken_logs-0.1.1.dist-info/METADATA
harken_logs-0.1.1.dist-info/WHEEL
harken_logs-0.1.1.dist-info/RECORD
